atc_demo_ui/__init__.py
atc_demo_ui/settings.py
atc_demo_ui/urls.py
atc_demo_ui/views.py
atc_demo_ui/static/css/atc.css
atc_demo_ui/static/js/.atc-profiles.js.swp
atc_demo_ui/static/js/atc-auth.js
atc_demo_ui/static/js/atc-profiles.js
atc_demo_ui/static/js/atc-shaping.js
atc_demo_ui/static/js/atc-utils.js
atc_demo_ui/static/js/atc.js
atc_demo_ui/static/vendor/react/JSXTransformer-0.13.3.js
atc_demo_ui/static/vendor/react/react-0.13.3.js
atc_demo_ui/templates/atc_demo_ui/base.html
atc_demo_ui/templates/atc_demo_ui/index.html
atc_demo_ui/templates/atc_demo_ui/shaping_settings.html
django_atc_demo_ui-0.1.6.dist-info/DESCRIPTION.rst
django_atc_demo_ui-0.1.6.dist-info/METADATA
django_atc_demo_ui-0.1.6.dist-info/RECORD
django_atc_demo_ui-0.1.6.dist-info/WHEEL
django_atc_demo_ui-0.1.6.dist-info/metadata.json
django_atc_demo_ui-0.1.6.dist-info/top_level.txt
