Metadata-Version: 2.0
Name: django-atc-demo-ui
Version: 0.1.6
Summary: Demo Web UI for ATC
Home-page: https://github.com/facebook/augmented-traffic-control
Author: Emmanuel Bretelle
Author-email: chantra@fb.com
License: UNKNOWN
Platform: UNKNOWN
Classifier: Programming Language :: Python
Requires-Dist: django-atc-api
Requires-Dist: django-bootstrap-themes (==3.3.6)
Requires-Dist: django-static-jquery (==1.11.1)
